LICENSE
README.rst
setup.py
speedometer.py
Speedometer.egg-info/PKG-INFO
Speedometer.egg-info/SOURCES.txt
Speedometer.egg-info/dependency_links.txt
Speedometer.egg-info/entry_points.txt
Speedometer.egg-info/requires.txt
Speedometer.egg-info/top_level.txt