Metadata-Version: 2.1
Name: Speedometer
Version: 2.9
Summary: Console monitor of the rate of data across a network connection or data being stored in a file.
Home-page: http://excess.org/speedometer/
Author: Ian Ward
Author-email: ian@excess.org
License: LGPL
Keywords: network bandwidth monitor system speed download file progress console
Platform: Linux
Classifier: Development Status :: 4 - Beta
Classifier: Environment :: Console
Classifier: Environment :: Console :: Curses
Classifier: Intended Audience :: Developers
Classifier: Intended Audience :: System Administrators
Classifier: License :: OSI Approved :: GNU Library or Lesser General Public License (LGPL)
Classifier: Operating System :: POSIX :: Linux
Classifier: Topic :: System :: Monitoring
Classifier: Topic :: System :: Networking :: Monitoring
License-File: LICENSE
